example_pkg/__init__.py
new_package-0.0.1.dist-info/LICENSE.txt
new_package-0.0.1.dist-info/METADATA
new_package-0.0.1.dist-info/WHEEL
new_package-0.0.1.dist-info/top_level.txt
new_package-0.0.1.dist-info/RECORD
