Metadata-Version: 2.1
Name: new-package
Version: 0.0.1
Summary: My_new_python_package
Home-page: https://github.com/pypa/sampleproject
Author: sid
Author-email: sid.garg@gmail.com
License: UNKNOWN
Platform: UNKNOWN
Classifier: Programming Language :: Python :: 3
Classifier: License :: OSI Approved :: MIT License
Classifier: Operating System :: OS Independent
Requires-Python: >=3.6
